ipyiframe/__init__.py
ipyiframe/__meta__.py
ipyiframe/ipyiframe.json
ipyiframe/widget_iframe.py
ipyiframe/widget_util.py
ipyiframe/static/extension.js
ipyiframe/static/index.js
ipyiframe/static/index.js.map
ipyiframe-0.1.0.data/data/etc/jupyter/nbconfig/notebook.d/ipyiframe.json
ipyiframe-0.1.0.data/data/share/jupyter/nbextensions/ipyiframe/extension.js
ipyiframe-0.1.0.data/data/share/jupyter/nbextensions/ipyiframe/index.js
ipyiframe-0.1.0.data/data/share/jupyter/nbextensions/ipyiframe/index.js.map
ipyiframe-0.1.0.dist-info/METADATA
ipyiframe-0.1.0.dist-info/RECORD
ipyiframe-0.1.0.dist-info/WHEEL
ipyiframe-0.1.0.dist-info/top_level.txt
